{
    "diverta2019": 853,
    "abc126": 1048,
    "acl1": 940,
    "agc056": 972,
    "abc231": 781,
    "arc132": 1357,
    "arc136": 977,
    "abc242": 1175,
    "arc137": 646,
    "arc138": 1180,
    "arc139": 944,
    "agc057": 950,
    "arc140": 1427,
    "arc141": 976,
    "abc259": 1170,
    "arc144": 1204,
    "arc145": 1324,
    "abc262": 1290,
    "abc263": 867,
    "arc146": 590,
    "arc147": 153,
    "arc148": 1198,
    "arc149": 969,
    "abc272": 1207,
    "arc150": 323,
    "abc274": 1303,
    "abc276": 907,
    "abc277": 1117,
    "abc281": 1604,
    "abc283": 1368,
    "abc288": 1523,
    "abc291": 450,
    "abc292": 698,
    "abc298": 997,
    "abc300": 603,
    "abc304": 1334,
    "abc308": 989,
    "abc314": 827,
    "abc326": 475,
    "arc169": 393,
    "abc337": 1046,
    "abc339": 1253
}