{
    "abc163": 816,
    "agc046": 1311,
    "abc253": 1519,
    "arc141": 1636,
    "abc254": 1037,
    "abc255": 1043,
    "abc256": 1749,
    "arc142": 1298,
    "abc257": 1478,
    "arc143": 1601,
    "abc258": 1441,
    "abc259": 1670,
    "arc144": 1253,
    "abc260": 1745,
    "abc261": 966,
    "arc145": 1209,
    "abc262": 1269,
    "abc263": 1760,
    "abc264": 1407,
    "agc058": 782,
    "arc146": 1613,
    "abc265": 2014,
    "abc267": 1511,
    "arc147": 1043,
    "abc268": 1225,
    "arc148": 1256,
    "abc269": 1228,
    "abc270": 1518,
    "abc271": 1446,
    "abc272": 1692
}