{
    "abc211": 1759,
    "abc213": 2400,
    "abc214": 2194,
    "abc215": 1690,
    "abc219": 2131,
    "abc220": 2189,
    "abc221": 2106,
    "abc224": 2400,
    "abc226": 2290,
    "abc227": 2054,
    "abc228": 2400,
    "abc230": 29,
    "agc056": 972,
    "abc241": 792,
    "arc141": 256,
    "abc255": 2400,
    "abc256": 2400,
    "arc142": 149,
    "abc257": 39,
    "abc258": 1850,
    "abc259": 2400,
    "arc144": 1470,
    "abc261": 53,
    "abc262": 2022,
    "abc263": 2400,
    "abc266": 44,
    "abc267": 1281,
    "abc268": 43,
    "abc270": 48,
    "abc277": 35,
    "abc278": 1506,
    "abc284": 46,
    "abc296": 44,
    "arc159": 245
}