{
    "abc249": 157,
    "agc057": 950,
    "abc252": 490,
    "abc253": 680,
    "abc254": 330,
    "abc256": 235,
    "abc257": 562,
    "abc261": 198,
    "abc262": 92,
    "abc263": 600,
    "abc264": 848,
    "arc146": 118,
    "abc265": 307,
    "abc267": 156,
    "abc270": 121,
    "abc271": 922,
    "abc272": 736,
    "abc273": 980,
    "abc274": 718,
    "abc276": 763,
    "abc277": 652,
    "abc278": 853,
    "abc279": 675,
    "abc298": 1243,
    "abc299": 1292,
    "abc304": 1315,
    "abc306": 1448,
    "abc330": 73,
    "abc333": 1406
}