{
    "abc058": 1600,
    "abc064": 1600,
    "abc073": 1426,
    "abc075": 1600,
    "abc076": 1600,
    "abc080": 1600,
    "abc084": 1600,
    "abc118": 1600,
    "abc120": 1600,
    "abc121": 1600,
    "abc125": 1600,
    "abc126": 2400,
    "abc131": 2283,
    "abc139": 2400,
    "abc147": 2400,
    "abc148": 2400,
    "abc149": 887,
    "abc150": 2400,
    "abc151": 1836,
    "abc152": 2088,
    "abc154": 2400,
    "abc155": 1738,
    "abc158": 1836,
    "abc160": 2063,
    "abc163": 2400,
    "abc164": 2400,
    "abc165": 2196,
    "abc167": 2319,
    "abc171": 2400,
    "abc174": 1922,
    "abc176": 2400,
    "abc178": 2400,
    "abc179": 2347,
    "abc180": 2400,
    "abc182": 2400,
    "abc183": 2400,
    "abc184": 1861,
    "abc185": 1517,
    "abc188": 2400,
    "abc191": 1057,
    "abc192": 2157,
    "abc193": 2400,
    "abc194": 1450,
    "abc195": 2096,
    "abc198": 2400,
    "abc199": 2400,
    "abc201": 2400,
    "abl": 1558,
    "aising2020": 2400,
    "arc063": 2684,
    "arc064": 2928,
    "arc065": 2472,
    "arc076": 2697,
    "arc078": 2791,
    "arc079": 2945,
    "arc082": 2446,
    "arc084": 3069,
    "arc085": 2982,
    "arc086": 2977,
    "arc087": 3073,
    "arc091": 2273,
    "arc094": 2451,
    "arc095": 2520,
    "arc096": 3200,
    "arc097": 3200,
    "arc098": 1429,
    "arc099": 2851,
    "arc100": 1682,
    "arc104": 2429,
    "arc105": 1021,
    "arc107": 3200,
    "arc109": 2039,
    "arc110": 2439,
    "arc111": 1881,
    "arc113": 2672,
    "arc114": 2630,
    "arc115": 2202,
    "arc116": 2629,
    "arc117": 3200,
    "arc118": 1529,
    "arc119": 2379,
    "diverta2019-2": 2623,
    "hhkb2020": 100,
    "hitachi2020": 2672,
    "keyence2020": 3200,
    "m-solutions2019": 2209,
    "m-solutions2020": 2400,
    "nomura2020": 2653,
    "panasonic2020": 213,
    "tenka1-2017": 2877,
    "tenka1-2019": 2534,
    "tokiomarine2020": 2421,
    "yahoo-procon2019-qual": 2297
}