{
    "abc126": 1082,
    "abc149": 1609,
    "abc150": 2021,
    "abc163": 1917,
    "abc267": 34,
    "arc147": 153,
    "abc270": 2400,
    "abc271": 2400,
    "abc272": 895,
    "abc273": 510,
    "abc274": 1882,
    "abc275": 1638,
    "abc276": 2333,
    "abc277": 2400,
    "abc278": 1670,
    "abc279": 2159,
    "abc280": 2198,
    "abc281": 1653,
    "abc282": 1413,
    "abc283": 80,
    "abc284": 2152,
    "abc285": 2196,
    "abc286": 2400,
    "abc287": 2006,
    "abc288": 2127,
    "abc289": 2167,
    "abc290": 42,
    "abc291": 2400,
    "abc292": 1926,
    "abc293": 1777,
    "abc294": 1652,
    "abc295": 2384,
    "abc296": 1360,
    "abc297": 2400,
    "abc298": 1864,
    "abc299": 2102,
    "abc300": 2400,
    "abc301": 1885,
    "abc303": 2212,
    "abc304": 1984,
    "abc305": 2393,
    "abc306": 1932
}