{
    "abc149": 1749,
    "abc227": 1554,
    "abc228": 2264,
    "abc229": 1864,
    "abc230": 29,
    "abc233": 36,
    "abc234": 47,
    "abc235": 36,
    "abc236": 35,
    "abc241": 39,
    "abc242": 1614,
    "abc243": 2400,
    "arc137": 172,
    "abc244": 41,
    "arc138": 260,
    "abc249": 52,
    "abc250": 1286,
    "abc251": 1878,
    "abc252": 2100,
    "abc253": 1879,
    "abc254": 1920,
    "abc255": 1873,
    "abc256": 1965,
    "abc257": 1725,
    "abc258": 1835,
    "abc259": 1950,
    "abc260": 1786,
    "abc262": 2010,
    "abc263": 1824,
    "abc264": 2001,
    "abc266": 44,
    "abc267": 2271,
    "abc268": 1198,
    "abc269": 1675,
    "abc270": 1087,
    "abc273": 88,
    "abc275": 1957,
    "arc152": 130,
    "abc280": 1443,
    "abc284": 2400,
    "abc288": 2065,
    "abc289": 38,
    "abc291": 44,
    "abc304": 2400,
    "abc306": 2400,
    "arc162": 1099,
    "abc307": 2130,
    "abc308": 1688,
    "abc309": 2035,
    "abc310": 1917,
    "abc311": 2088,
    "abc312": 1957,
    "abc313": 425,
    "abc314": 2400,
    "agc064": 1450,
    "abc315": 1957,
    "abc317": 1817,
    "abc318": 1714,
    "abc319": 1815,
    "abc320": 2196,
    "abc321": 1845,
    "abc322": 1662,
    "abc323": 1677,
    "arc166": 358,
    "abc324": 855,
    "abc325": 2400,
    "abc326": 2139,
    "abc327": 1338,
    "abc328": 1145,
    "abc329": 34
}