{
    "abc261": 1408,
    "arc145": 842,
    "abc263": 927,
    "abc269": 950,
    "abc272": 1457,
    "abc275": 1286,
    "abc276": 1503,
    "abc278": 1238,
    "abc279": 272,
    "abc281": 1618,
    "abc282": 1035,
    "abc284": 1525,
    "arc153": 1211,
    "abc287": 1505,
    "arc155": 445,
    "abc288": 1147,
    "abc289": 1519,
    "arc156": 811,
    "abc290": 1436,
    "arc157": 1130,
    "abc291": 1689,
    "abc292": 1620,
    "abc293": 1861,
    "abc295": 244,
    "abc296": 1222,
    "abc301": 965,
    "abc306": 325,
    "arc163": 166,
    "abc309": 39,
    "arc164": 203,
    "abc311": 1397,
    "abc312": 1004,
    "abc313": 1428,
    "abc314": 416,
    "abc319": 1506,
    "abc320": 1099,
    "abc322": 37,
    "abc324": 618,
    "abc325": 39,
    "abc327": 319
}