{
    "abc051": 1600,
    "abc054": 1600,
    "abc057": 1600,
    "abc064": 1600,
    "abc070": 1600,
    "tenka1-2017": 1796,
    "abc079": 1600,
    "abc084": 1600,
    "abc085": 1600,
    "abc088": 1600,
    "abc089": 1600,
    "abc096": 1600,
    "abc099": 1600,
    "abc100": 1600,
    "abc103": 1600,
    "abc104": 1600,
    "abc105": 1600,
    "abc106": 1600,
    "abc109": 1600,
    "abc110": 1600,
    "abc112": 1558,
    "abc113": 1600,
    "abc114": 1600,
    "abc115": 1600,
    "aising2019": 2035,
    "abc116": 1600,
    "abc117": 1419,
    "abc118": 1600,
    "abc119": 1600,
    "abc120": 1600,
    "abc121": 1600,
    "abc122": 1114,
    "abc123": 1600,
    "abc124": 1600,
    "diverta2019": 2282,
    "abc126": 1687,
    "abc127": 1972,
    "abc128": 2093,
    "abc149": 2264,
    "abc150": 1801,
    "abc158": 2187,
    "panasonic2020": 2131
}