{
    "abc085": 1571,
    "abc089": 1387,
    "abc099": 979,
    "abc100": 1286,
    "abc103": 1600,
    "abc109": 1570,
    "abc110": 1584,
    "abc112": 1385,
    "abc113": 1361,
    "abc114": 1600,
    "abc115": 1370,
    "abc116": 554,
    "abc117": 1260,
    "abc118": 1600,
    "abc119": 1600,
    "abc120": 1534,
    "abc123": 1183,
    "abc125": 1194,
    "diverta2019": 1792,
    "abc126": 1990,
    "abc230": 29,
    "abc232": 33,
    "abc233": 36,
    "arc138": 260,
    "abc277": 35,
    "abc307": 1293,
    "abc331": 40
}