{
    "abc051": 1516,
    "abc054": 1600,
    "abc057": 1600,
    "abc061": 1600,
    "abc064": 1432,
    "abc073": 1600,
    "abc075": 1600,
    "abc076": 1600,
    "abc079": 1600,
    "abc080": 1291,
    "abc084": 1600,
    "abc085": 989,
    "abc088": 1600,
    "abc089": 1600,
    "abc096": 1600,
    "abc099": 1600,
    "abc100": 1600,
    "abc103": 1600,
    "abc104": 1600,
    "abc105": 1600,
    "abc106": 1600,
    "abc109": 1600,
    "abc110": 1600,
    "abc112": 1600,
    "abc113": 1600,
    "abc114": 1600,
    "abc115": 1405,
    "abc117": 1600,
    "abc118": 1600,
    "abc119": 1600,
    "abc120": 1600,
    "abc121": 1600,
    "abc122": 1600,
    "abc124": 1600,
    "abc125": 1600,
    "abc126": 1680,
    "abc127": 2282,
    "abc128": 2114,
    "abc130": 2226,
    "abc131": 1812,
    "abc132": 2400,
    "abc133": 1719,
    "abc134": 2155,
    "abc137": 1928,
    "abc138": 1951,
    "abc139": 2400,
    "abc140": 1901,
    "abc141": 2330,
    "abc142": 2229,
    "abc143": 1905,
    "abc144": 2043,
    "abc145": 2131,
    "abc146": 1803,
    "abc147": 2227,
    "abc148": 2400,
    "abc149": 2108,
    "abc150": 1827,
    "abc151": 1785,
    "abc152": 2068,
    "abc153": 2400,
    "abc154": 2242,
    "abc155": 2067,
    "abc156": 1305,
    "abc157": 2014,
    "abc158": 1607,
    "abc162": 1843,
    "abc163": 919,
    "abc164": 2400,
    "abc165": 2164,
    "abc166": 2227,
    "abc167": 2122,
    "abc168": 1799,
    "abc169": 1802,
    "abc176": 1989,
    "abc177": 2400,
    "abc178": 1802,
    "abc179": 2086,
    "abc180": 2341,
    "abc183": 2372,
    "abc200": 2063,
    "abc201": 2325,
    "abc202": 2335,
    "abc205": 2400,
    "abc206": 1645,
    "abc207": 1546,
    "abc211": 2400,
    "abc212": 1652,
    "abc213": 2209,
    "abc214": 2117,
    "abc215": 2046,
    "abc216": 2037,
    "abc217": 2101,
    "abc218": 2166,
    "abc219": 1595,
    "abc224": 2288,
    "abc225": 1773,
    "abc235": 1913,
    "abc236": 1659,
    "abc237": 2400,
    "abc238": 1831,
    "abc240": 1822,
    "abc241": 2197,
    "abc246": 2074,
    "abc249": 2363,
    "abc250": 2077,
    "abc251": 1755,
    "abc253": 80,
    "abc263": 1561,
    "abc264": 1554,
    "abc266": 1494,
    "abc267": 2397,
    "abc276": 2137,
    "abc277": 2172,
    "abc278": 2133,
    "abc279": 2391,
    "abl": 1628,
    "agc058": 1106,
    "arc141": 256,
    "arc152": 1264,
    "diverta2019": 2358,
    "hhkb2020": 1773,
    "sumitrust2019": 1577,
    "tenka1-2017": 1691,
    "abc280": 1237,
    "agc059": 1811,
    "abc281": 2135,
    "abc282": 1461,
    "abc283": 2036
}