{
    "abc057": 1574,
    "abc061": 1600,
    "abc064": 1141,
    "abc073": 1600,
    "abc075": 1065,
    "abc076": 1600,
    "abc079": 1600,
    "abc080": 1600,
    "abc084": 1503,
    "abc085": 1298,
    "abc088": 1600,
    "abc089": 1600,
    "abc096": 1600,
    "abc100": 1600,
    "soundhound2018-summer-qual": 1876,
    "abc104": 1600,
    "abc105": 1600,
    "abc106": 1600,
    "abc109": 1600,
    "abc113": 1600,
    "abc114": 1234,
    "abc115": 1600,
    "abc118": 1600,
    "abc120": 1600,
    "abc121": 1600,
    "abc122": 1519,
    "abc124": 1360,
    "abc125": 1600,
    "abc126": 2076,
    "abc129": 2156,
    "abc130": 1955,
    "abc132": 1781,
    "abc147": 1825,
    "abc149": 1071,
    "abc152": 1041,
    "abc184": 1810,
    "abc185": 1533,
    "abc192": 397,
    "abc201": 1640,
    "abc317": 48
}