{
    "abc163": 159,
    "agc046": 524,
    "acl1": 940,
    "agc056": 972,
    "arc134": 142,
    "abc267": 222,
    "abc268": 510,
    "abc269": 413,
    "abc270": 387,
    "abc271": 415,
    "abc298": 563,
    "abc299": 375,
    "abc304": 451,
    "abc305": 212,
    "abc306": 183,
    "abc308": 127,
    "abc312": 99,
    "abc313": 267,
    "abc314": 184,
    "abc315": 116,
    "abc317": 643,
    "abc319": 102,
    "abc320": 94,
    "abc322": 37,
    "abc323": 41,
    "abc324": 86,
    "abc325": 90,
    "abc326": 262,
    "abc328": 85,
    "abc330": 96,
    "abc331": 90,
    "arc169": 393,
    "abc334": 65,
    "abc335": 213,
    "abc339": 114,
    "abc340": 118,
    "abc343": 94
}