{
    "tenka1-2017": 2809,
    "abc228": 2400,
    "abc230": 2353,
    "agc056": 972,
    "arc131": 101,
    "abc232": 33,
    "abc233": 36,
    "abc236": 2400,
    "arc134": 2470,
    "abc237": 2400,
    "abc238": 43,
    "arc135": 222,
    "abc240": 29,
    "abc241": 2400,
    "arc136": 2008,
    "abc242": 1946,
    "abc243": 41,
    "arc137": 172,
    "abc244": 41,
    "abc245": 2400,
    "abc246": 42,
    "abc248": 38,
    "abc252": 2400,
    "abc253": 33,
    "arc141": 256,
    "abc254": 608,
    "abc255": 86,
    "abc256": 35,
    "abc257": 39,
    "arc143": 2355,
    "abc258": 2400,
    "abc259": 2368,
    "abc260": 2217,
    "abc261": 2400,
    "arc145": 2131,
    "abc262": 2400,
    "abc263": 2400,
    "abc264": 2389,
    "abc265": 2400,
    "abc266": 2400,
    "abc267": 2400,
    "abc268": 2400,
    "abc269": 2400,
    "abc270": 2400,
    "abc271": 2333,
    "abc272": 2400,
    "abc273": 2400,
    "abc274": 2400,
    "abc275": 2400,
    "abc276": 2400,
    "abc277": 2400,
    "abc278": 2400,
    "abc279": 2400,
    "abc280": 1277,
    "agc059": 1320,
    "abc281": 2400,
    "abc282": 1817,
    "abc283": 2400,
    "agc060": 1696,
    "abc284": 2400,
    "abc286": 2400,
    "arc154": 170,
    "abc287": 2400,
    "arc155": 445,
    "abc288": 37,
    "abc289": 38,
    "agc061": 1247,
    "abc290": 42,
    "arc157": 1852,
    "abc291": 2400,
    "abc292": 2041,
    "abc293": 1475,
    "arc158": 2369,
    "abc294": 39,
    "abc295": 2400,
    "abc296": 1422,
    "arc159": 2323,
    "abc297": 51,
    "abc298": 2400,
    "abc299": 2133,
    "abc300": 1348,
    "abc301": 53,
    "arc160": 364,
    "abc302": 2400,
    "agc062": 751,
    "abc303": 1816,
    "arc161": 131,
    "abc304": 2400,
    "abc305": 2400,
    "abc306": 2400,
    "arc162": 198,
    "abc307": 2092,
    "abc308": 2400,
    "arc163": 166,
    "abc309": 39,
    "arc164": 1067,
    "abc310": 84,
    "abc311": 50,
    "abc312": 2400,
    "agc063": 650,
    "abc313": 63,
    "abc314": 47,
    "agc064": 614,
    "abc315": 2400,
    "abc317": 48,
    "abc318": 1023,
    "wtf22-day1-open": 1523,
    "abc319": 1353,
    "abc320": 2375,
    "arc165": 2445,
    "abc321": 2400,
    "abc322": 37,
    "abc323": 2400,
    "arc166": 358,
    "abc324": 671,
    "abc325": 2400,
    "abc326": 1163,
    "abc327": 49,
    "abc328": 39,
    "arc168": 2615,
    "arc169": 393,
    "abc332": 2400,
    "abc333": 2005,
    "abc335": 52,
    "abc336": 53,
    "abc337": 42,
    "arc170": 263,
    "abc338": 53,
    "abc339": 1019,
    "arc171": 246,
    "abc340": 54,
    "abc341": 838,
    "abc342": 568,
    "abc343": 43,
    "abc344": 290,
    "arc173": 416,
    "abc347": 43,
    "agc066": 1384,
    "abc348": 37,
    "abc349": 2400,
    "abc350": 2336,
    "arc176": 2629,
    "abc351": 43,
    "abc352": 2400,
    "abc353": 770,
    "abc354": 38,
    "arc178": 2753,
    "abc355": 26,
    "abc356": 48,
    "arc179": 199,
    "abc357": 39,
    "abc358": 2400
}