{
    "abc105": 1190,
    "abc118": 1490,
    "abc120": 1165,
    "abc121": 402,
    "abc122": 630,
    "abc123": 1371,
    "abc124": 1004,
    "diverta2019": 816,
    "abc149": 2057,
    "abc150": 2063,
    "abc162": 2023,
    "abc163": 2400,
    "abc164": 2400,
    "abc165": 2058,
    "abc166": 2125,
    "abc167": 2400,
    "abc168": 2060,
    "abc169": 2019,
    "abc170": 2400,
    "abc171": 2400,
    "abc172": 2400,
    "abc173": 2000,
    "aising2020": 2400,
    "m-solutions2020": 2031,
    "abc174": 2196,
    "abc175": 12,
    "abc176": 1835,
    "abc177": 2283,
    "abc178": 2400,
    "abc179": 1995,
    "abl": 1747,
    "hhkb2020": 2400,
    "abc183": 1551,
    "abc184": 2400,
    "abc185": 1491,
    "abc187": 2109,
    "abc189": 1948,
    "abc190": 2251,
    "abc191": 2400,
    "abc192": 1851,
    "abc193": 1793,
    "abc194": 1427,
    "abc195": 1816,
    "abc197": 2400,
    "abc198": 1821,
    "jsc2021": 1766,
    "abc201": 2400,
    "abc203": 2400,
    "abc204": 2400,
    "abc206": 2143,
    "abc207": 1480,
    "abc209": 2159,
    "abc210": 2400,
    "abc211": 2400,
    "abc212": 2299,
    "abc213": 2056,
    "abc214": 1823,
    "abc216": 2001,
    "abc217": 2154,
    "abc218": 2381,
    "abc220": 2400,
    "abc221": 2127,
    "abc224": 2400,
    "abc227": 2117,
    "abc237": 2400,
    "abc292": 2400,
    "abc293": 1776,
    "abc294": 2164,
    "abc298": 2034,
    "abc300": 44,
    "abc301": 53,
    "abc303": 44,
    "abc309": 1437,
    "abc311": 2157,
    "abc317": 2400,
    "abc318": 2335,
    "abc319": 36,
    "abc320": 2400,
    "abc321": 2266,
    "abc322": 1736
}