{
    "abc266": 1613,
    "arc147": 1501,
    "abc289": 890,
    "abc295": 1361,
    "abc298": 1845,
    "abc299": 1628,
    "abc300": 1678,
    "abc304": 2025,
    "abc307": 1876,
    "abc309": 2212,
    "abc310": 1963,
    "abc312": 2106,
    "abc313": 2400,
    "abc315": 1749,
    "abc317": 2130,
    "abc318": 2011,
    "abc319": 2166,
    "abc320": 2232,
    "abc322": 1569,
    "abc323": 2008,
    "abc324": 1796,
    "abc325": 2400,
    "abc326": 2400,
    "abc327": 1611,
    "abc329": 1864,
    "abc330": 1851,
    "abc331": 2205,
    "abc332": 2036,
    "abc334": 2177,
    "abc336": 1744
}