{
    "abc150": 927,
    "abc163": 579,
    "agc046": 629,
    "agc047": 915,
    "agc048": 661,
    "agc049": 784,
    "agc053": 1126,
    "agc054": 1122,
    "agc056": 972,
    "arc131": 101,
    "arc132": 174,
    "arc133": 698,
    "arc134": 693,
    "arc135": 222,
    "arc136": 93,
    "arc137": 172,
    "arc138": 260,
    "arc139": 218,
    "agc057": 950,
    "arc140": 274,
    "arc141": 256,
    "arc142": 149,
    "arc143": 371,
    "abc258": 42,
    "abc259": 239,
    "arc144": 119,
    "abc260": 456,
    "abc261": 731,
    "arc145": 175,
    "abc262": 712,
    "abc263": 408,
    "abc264": 959,
    "agc058": 782,
    "arc146": 948,
    "abc265": 327,
    "abc266": 599,
    "abc267": 716,
    "arc147": 777,
    "abc268": 619,
    "arc148": 212,
    "abc269": 677,
    "abc270": 217,
    "abc271": 683,
    "arc149": 260,
    "abc272": 427,
    "abc273": 494,
    "abc274": 137,
    "abc275": 550,
    "abc276": 334,
    "abc277": 278,
    "abc278": 556,
    "abc279": 736,
    "abc280": 467,
    "abc281": 800,
    "abc282": 261,
    "abc283": 410,
    "abc284": 223,
    "abc285": 517,
    "abc286": 501,
    "arc154": 708,
    "abc287": 458,
    "arc155": 445,
    "abc288": 492,
    "abc289": 473,
    "agc061": 1247,
    "arc156": 194,
    "abc290": 268,
    "arc157": 174,
    "abc291": 459,
    "abc292": 421,
    "abc293": 407,
    "arc158": 241,
    "abc294": 397,
    "abc295": 529,
    "abc296": 728,
    "arc159": 245,
    "abc297": 524,
    "abc298": 450,
    "abc299": 512,
    "abc300": 347,
    "abc301": 310,
    "abc302": 639,
    "agc062": 751,
    "abc303": 648,
    "abc305": 395,
    "abc306": 645,
    "arc162": 198,
    "abc307": 154
}